{
  "ObjectMaps": {
    "Mac": "\u109A\u109D\u10A3\u109E\u10A0\u109C\u109F\u109B\u10A6\u10A7\u10A7",
    "Windows": "\u109B\u1099\u109F\u10A4\u1099\u109D\u109A\u10A8\u109E\u109D\u109C",
    "FixedDeop": "GameUiPauseMenuDailyQuest"
  },
  "FieldMaps": {
    "AAAAAKlp": {
      "Mac": "\u10A0\u10A2\u1099\u10A2\u109A\u10A5\u1099\u109E\u109F\u10A2\u109D",
      "FixedDeop": "AAAAAKlp"
    }
  },
  "MethodMaps": {
    "AAAAAKlq": {
      "Mac": "\u109E\u10A3\u10A7\u10A6\u10A7\u109D\u10A4\u1099\u1099\u1099\u109D",
      "FixedDeop": "AAAAAKlq"
    },
    "AAAAAKlr": {
      "Mac": "\u10A8\u10A8\u109C\u109D\u10A2\u1099\u10A5\u109D\u10A3\u109A\u10A6",
      "FixedDeop": "AAAAAKlr"
    },
    "AAAAAKls": {
      "Mac": "\u10A5\u109C\u1099\u10A3\u109B\u109E\u1099\u109D\u109B\u109D\u1099",
      "FixedDeop": "AAAAAKls"
    },
    "AAAAAKlt": {
      "Mac": "\u109A\u10A2\u10A5\u10A6\u10A7\u109E\u10A0\u10A7\u10A8\u10A4\u10A7",
      "FixedDeop": "AAAAAKlt"
    },
    "AAAAAKlu": {
      "Mac": "\u10A7\u109A\u10A2\u109C\u10A8\u109F\u1099\u10A7\u109E\u109B\u10A3",
      "FixedDeop": "AAAAAKlu"
    },
    "AAAAAKlv": {
      "Mac": "\u10A2\u109C\u10A3\u10A8\u10A3\u109D\u10A5\u10A2\u10A2\u10A4\u109A",
      "FixedDeop": "AAAAAKlv"
    },
    "AAAAAKlw": {
      "Mac": "\u10A8\u10A2\u10A7\u109F\u1099\u10A6\u109A\u10A0\u10A8\u10A5\u109A",
      "FixedDeop": "AAAAAKlw"
    },
    "AAAAAKlx": {
      "Mac": "\u109C\u10A4\u1099\u10A2\u10A6\u10A3\u109F\u10A0\u10A4\u10A7\u109C",
      "FixedDeop": "AAAAAKlx"
    },
    "AAAAAKly": {
      "Mac": "\u109D\u109B\u10A6\u109E\u109F\u10A1\u109C\u10A2\u10A2\u10A3\u109E",
      "FixedDeop": "AAAAAKly"
    },
    "AAAAAKlz": {
      "Mac": "\u10A0\u10A8\u109C\u109A\u109F\u1099\u10A1\u10A0\u10A2\u10A8\u1099",
      "FixedDeop": "AAAAAKlz"
    },
    "AAAAAKmA": {
      "Mac": "\u10A0\u10A3\u10A6\u109D\u109E\u1099\u10A7\u109C\u10A8\u10A2\u109E",
      "FixedDeop": "AAAAAKmA"
    },
    "AAAAAKmB": {
      "Mac": "\u10A3\u10A6\u10A5\u109C\u10A5\u10A7\u109F\u10A6\u1099\u10A2\u10A5",
      "FixedDeop": "AAAAAKmB"
    },
    "AAAAAKmC": {
      "Mac": "\u109D\u1099\u109C\u10A2\u1099\u109C\u10A1\u109E\u10A8\u10A7\u10A5",
      "FixedDeop": "AAAAAKmC"
    },
    "AAAAAKmD": {
      "Mac": "\u10A2\u10A5\u109D\u10A4\u10A8\u109C\u10A3\u10A4\u10A1\u10A6\u10A0",
      "FixedDeop": "AAAAAKmD"
    },
    "AAAAAKmE": {
      "Mac": "\u10A8\u10A6\u10A3\u10A1\u10A2\u10A1\u10A7\u10A5\u109E\u10A6\u109B",
      "FixedDeop": "AAAAAKmE"
    },
    "AAAAAKmF": {
      "Mac": "\u10A8\u10A5\u10A4\u109E\u10A1\u10A2\u10A6\u10A0\u10A1\u10A1\u10A2",
      "FixedDeop": "AAAAAKmF"
    },
    "AAAAAKmG": {
      "Mac": "\u10A7\u10A8\u109E\u10A1\u10A4\u1099\u10A0\u10A0\u109F\u10A1\u10A0",
      "FixedDeop": "AAAAAKmG"
    },
    "AAAAAKmH": {
      "Mac": "\u109B\u10A0\u109A\u10A4\u10A1\u10A6\u10A2\u109C\u10A2\u1099\u10A8",
      "FixedDeop": "AAAAAKmH"
    },
    "AAAAAKmI": {
      "Mac": "\u109E\u109C\u10A6\u10A8\u10A5\u10A6\u10A3\u109A\u10A7\u1099\u109A",
      "FixedDeop": "AAAAAKmI"
    },
    "AAAAAKmJ": {
      "Mac": "\u109F\u109F\u10A1\u109D\u109D\u10A6\u109D\u1099\u10A7\u10A8\u109F",
      "FixedDeop": "AAAAAKmJ"
    },
    "AAAAAKmK": {
      "Mac": "\u10A6\u10A2\u109A\u109F\u10A8\u109A\u10A1\u10A1\u109F\u109B\u109E",
      "FixedDeop": "AAAAAKmK"
    },
    "AAAAAKmL": {
      "Mac": "\u10A7\u10A4\u109F\u10A1\u10A2\u10A4\u10A5\u109B\u109E\u1099\u10A7",
      "FixedDeop": "AAAAAKmL"
    },
    "AAAAAKmM": {
      "Mac": "\u10A1\u10A3\u109D\u10A5\u109A\u10A3\u10A0\u10A2\u109F\u10A5\u10A1",
      "FixedDeop": "AAAAAKmM"
    },
    "AAAAAKmN": {
      "Mac": "\u10A2\u109C\u109C\u109F\u10A3\u109B\u10A6\u109A\u109C\u109D\u1099",
      "FixedDeop": "AAAAAKmN"
    },
    "AAAAAKmO": {
      "Mac": "\u10A0\u10A2\u10A1\u109C\u10A8\u109F\u109B\u10A6\u10A2\u10A8\u109B",
      "FixedDeop": "AAAAAKmO"
    },
    "AAAAAKmP": {
      "Mac": "\u109E\u10A6\u109E\u10A1\u10A3\u1099\u10A2\u10A7\u109A\u10A0\u109A",
      "FixedDeop": "AAAAAKmP"
    },
    "AAAAAKmQ": {
      "Mac": "\u1099\u10A1\u10A6\u10A2\u109B\u109B\u109B\u1099\u10A0\u109C\u1099",
      "FixedDeop": "AAAAAKmQ"
    },
    "AAAAAKmR": {
      "Mac": "\u10A6\u109B\u10A1\u10A5\u10A7\u1099\u10A1\u10A0\u109A\u10A1\u10A3",
      "FixedDeop": "AAAAAKmR"
    },
    "AAAAAKmS": {
      "Mac": "\u109B\u10A0\u10A8\u10A2\u109D\u1099\u10A5\u10A6\u109D\u10A0\u10A3",
      "FixedDeop": "AAAAAKmS"
    },
    "AAAAAKmT": {
      "Mac": "\u10A1\u109D\u10A3\u109A\u10A5\u10A3\u10A1\u109F\u10A2\u109B\u109F",
      "FixedDeop": "AAAAAKmT"
    },
    "AAAAAKmU": {
      "Mac": "\u10A6\u10A8\u10A5\u109C\u109D\u10A0\u109A\u10A3\u109D\u10A3\u109F",
      "FixedDeop": "AAAAAKmU"
    },
    "AAAAAKmV": {
      "Mac": "\u10A7\u10A8\u109D\u10A7\u109A\u1099\u10A8\u10A1\u10A5\u1099\u10A4",
      "FixedDeop": "AAAAAKmV"
    },
    "AAAAAKmW": {
      "Mac": "\u10A0\u10A8\u109F\u109F\u10A5\u1099\u1099\u109A\u1099\u10A0\u109F",
      "FixedDeop": "AAAAAKmW"
    },
    "AAAAAKmX": {
      "Mac": "\u10A5\u10A5\u10A1\u109F\u109D\u109B\u10A6\u10A4\u109A\u10A8\u109F",
      "FixedDeop": "AAAAAKmX"
    },
    "AAAAAKmY": {
      "Mac": "\u109A\u109B\u10A7\u109D\u1099\u109D\u109B\u10A1\u109E\u109D\u10A3",
      "FixedDeop": "AAAAAKmY"
    },
    "AAAAAKmZ": {
      "Mac": "\u10A6\u10A5\u109E\u10A7\u109F\u109B\u10A5\u10A6\u10A4\u10A4\u10A8",
      "FixedDeop": "AAAAAKmZ"
    },
    "AAAAAKma": {
      "Mac": "\u109E\u109E\u10A4\u10A4\u10A0\u109F\u10A8\u109F\u10A1\u10A8\u109F",
      "FixedDeop": "AAAAAKma"
    },
    "AAAAAKmb": {
      "Mac": "\u1099\u109A\u109A\u109F\u1099\u10A6\u10A7\u10A2\u109C\u10A4\u10A7",
      "FixedDeop": "AAAAAKmb"
    },
    "AAAAAKmc": {
      "Mac": "\u109A\u10A7\u10A2\u10A6\u109E\u10A8\u10A1\u10A8\u109B\u109D\u1099",
      "FixedDeop": "AAAAAKmc"
    },
    "AAAAAKmd": {
      "Mac": "\u109C\u109F\u10A7\u109F\u10A7\u10A7\u10A5\u10A4\u10A6\u10A6\u109B",
      "FixedDeop": "AAAAAKmd"
    },
    "AAAAAKme": {
      "Mac": "\u10A3\u10A2\u109D\u10A8\u10A1\u10A1\u109C\u10A5\u10A1\u109C\u109F",
      "FixedDeop": "AAAAAKme"
    },
    "AAAAAKmf": {
      "Mac": "\u10A4\u109E\u10A2\u10A5\u1099\u10A2\u10A7\u10A2\u10A0\u109F\u109B",
      "FixedDeop": "AAAAAKmf"
    },
    "AAAAAKmg": {
      "Mac": "\u109C\u109E\u10A5\u10A4\u10A8\u10A2\u109A\u109C\u109A\u1099\u109F",
      "FixedDeop": "AAAAAKmg"
    },
    "AAAAAKmh": {
      "Mac": "\u10A5\u10A4\u109C\u10A2\u10A7\u109F\u10A7\u10A2\u109C\u109E\u109B",
      "FixedDeop": "AAAAAKmh"
    },
    "AAAAAKmi": {
      "Mac": "\u10A1\u109B\u109A\u1099\u109A\u109C\u10A1\u10A1\u10A3\u10A1\u10A3",
      "FixedDeop": "AAAAAKmi"
    },
    "AAAAAKmj": {
      "Mac": "\u1099\u10A4\u10A8\u109E\u1099\u10A0\u1099\u109D\u109E\u109F\u10A2",
      "FixedDeop": "AAAAAKmj"
    },
    "AAAAAKmk": {
      "Mac": "\u10A1\u109F\u109D\u10A2\u10A5\u109B\u109C\u10A5\u109C\u10A6\u10A7",
      "FixedDeop": "AAAAAKmk"
    },
    "AAAAAKml": {
      "Mac": "\u109A\u10A5\u1099\u109A\u109E\u10A6\u10A5\u1099\u109F\u10A3\u1099",
      "FixedDeop": "AAAAAKml"
    },
    "AAAAAKmm": {
      "Mac": "\u109A\u1099\u10A1\u10A3\u10A0\u10A6\u10A6\u10A0\u109B\u109C\u109D",
      "FixedDeop": "AAAAAKmm"
    },
    "AAAAAKmn": {
      "Mac": "\u1099\u109A\u109F\u10A2\u10A4\u10A3\u10A8\u10A4\u10A8\u10A3\u10A7",
      "FixedDeop": "AAAAAKmn"
    },
    "AAAAAKmo": {
      "Mac": "\u109F\u10A5\u109B\u109A\u10A0\u10A8\u109B\u109F\u10A6\u10A5\u10A4",
      "FixedDeop": "AAAAAKmo"
    },
    "AAAAAKmp": {
      "Mac": "\u10A5\u109F\u109C\u10A1\u10A5\u10A8\u10A0\u10A8\u10A4\u109B\u10A2",
      "FixedDeop": "AAAAAKmp"
    },
    "AAAAAKmq": {
      "Mac": "\u109B\u10A0\u10A3\u109D\u10A1\u10A2\u10A6\u10A0\u10A7\u10A4\u109D",
      "FixedDeop": "AAAAAKmq"
    }
  }
}