{
  "ObjectMaps": {
    "Mac": "\u109B\u10A3\u1099\u10A0\u10A4\u10A7\u109C\u109C\u10A7\u10A4\u10A3",
    "Windows": "\u10A1\u1099\u10A8\u109F\u109C\u1099\u10A8\u109E\u10A4\u10A7\u1099",
    "FixedDeop": "AAAAABYe"
  },
  "FieldMaps": {},
  "MethodMaps": {
    "AAAAABYf": {
      "Mac": "\u109E\u10A7\u10A3\u10A0\u1099\u10A0\u109B\u109A\u109C\u10A7\u10A5",
      "FixedDeop": "AAAAABYf"
    },
    "AAAAABYg": {
      "Mac": "\u109D\u10A2\u10A4\u109E\u10A6\u10A7\u10A0\u109F\u10A3\u109C\u10A8",
      "FixedDeop": "AAAAABYg"
    },
    "AAAAABYh": {
      "Mac": "\u10A8\u10A4\u109E\u109A\u10A1\u109B\u109B\u10A8\u1099\u10A5\u10A4",
      "FixedDeop": "AAAAABYh"
    },
    "AAAAABYi": {
      "Mac": "\u10A2\u10A5\u10A5\u109B\u10A4\u10A8\u10A1\u10A8\u10A0\u10A0\u10A7",
      "FixedDeop": "AAAAABYi"
    },
    "AAAAABYj": {
      "Mac": "\u10A8\u10A0\u10A0\u109D\u10A7\u10A3\u10A3\u10A8\u10A8\u1099\u109D",
      "FixedDeop": "AAAAABYj"
    },
    "AAAAABYk": {
      "Mac": "\u10A2\u109A\u109A\u10A1\u10A3\u10A2\u10A6\u10A2\u10A5\u10A7\u10A5",
      "FixedDeop": "AAAAABYk"
    },
    "AAAAABYl": {
      "Mac": "\u10A7\u109E\u109F\u1099\u10A1\u10A3\u10A0\u10A1\u1099\u1099\u10A3",
      "FixedDeop": "AAAAABYl"
    },
    "AAAAABYm": {
      "Mac": "\u10A2\u10A2\u1099\u10A2\u10A5\u10A8\u10A5\u10A7\u109A\u109C\u10A1",
      "FixedDeop": "AAAAABYm"
    },
    "AAAAABYn": {
      "Mac": "\u10A7\u109D\u10A2\u10A2\u10A1\u10A0\u10A6\u10A2\u10A3\u109F\u10A3",
      "FixedDeop": "AAAAABYn"
    },
    "AAAAABYo": {
      "Mac": "\u109E\u1099\u109E\u109C\u10A1\u109C\u109F\u10A7\u109E\u109A\u10A1",
      "FixedDeop": "AAAAABYo"
    },
    "AAAAABYp": {
      "Mac": "\u109D\u109E\u10A0\u10A8\u109A\u10A0\u10A5\u10A5\u10A1\u109A\u109F",
      "FixedDeop": "AAAAABYp"
    },
    "AAAAABYq": {
      "Mac": "\u10A6\u10A1\u10A5\u10A7\u109C\u109E\u109A\u10A3\u10A2\u109E\u109E",
      "FixedDeop": "AAAAABYq"
    },
    "AAAAABYr": {
      "Mac": "\u109A\u10A6\u109E\u109C\u10A1\u10A7\u10A4\u109F\u109D\u10A6\u109D",
      "FixedDeop": "AAAAABYr"
    },
    "AAAAABYs": {
      "Mac": "\u10A1\u10A5\u10A8\u109E\u109B\u10A2\u109F\u1099\u10A0\u10A2\u109C",
      "FixedDeop": "AAAAABYs"
    },
    "AAAAABYt": {
      "Mac": "\u10A6\u10A2\u10A7\u10A2\u10A0\u10A2\u109D\u109A\u109E\u109B\u10A5",
      "FixedDeop": "AAAAABYt"
    },
    "AAAAABYu": {
      "Mac": "\u10A1\u109E\u10A7\u109F\u109B\u10A5\u10A5\u109F\u10A6\u10A6\u109C",
      "FixedDeop": "AAAAABYu"
    },
    "AAAAABYv": {
      "Mac": "\u10A1\u10A1\u109B\u109D\u10A6\u10A2\u1099\u10A7\u109E\u109D\u10A3",
      "FixedDeop": "AAAAABYv"
    },
    "AAAAABYw": {
      "Mac": "\u1099\u10A0\u1099\u10A4\u10A7\u109D\u109D\u10A0\u1099\u10A0\u109D",
      "FixedDeop": "AAAAABYw"
    },
    "AAAAABYx": {
      "Mac": "\u10A8\u10A5\u10A0\u10A2\u109B\u10A2\u10A8\u1099\u10A1\u10A5\u10A1",
      "FixedDeop": "AAAAABYx"
    },
    "AAAAABYy": {
      "Mac": "\u109E\u10A4\u109A\u10A2\u109C\u10A0\u10A1\u109C\u109D\u10A3\u10A2",
      "FixedDeop": "AAAAABYy"
    },
    "AAAAABYz": {
      "Mac": "\u10A0\u109C\u10A0\u109C\u109A\u1099\u10A1\u10A8\u109F\u10A8\u10A4",
      "FixedDeop": "AAAAABYz"
    },
    "AAAAABZA": {
      "Mac": "\u109E\u10A1\u10A0\u10A0\u10A5\u10A6\u10A7\u10A0\u10A8\u10A2\u109C",
      "FixedDeop": "AAAAABZA"
    },
    "AAAAABZB": {
      "Mac": "\u10A5\u10A1\u109D\u10A1\u10A0\u10A8\u10A4\u109A\u10A6\u10A1\u109E",
      "FixedDeop": "AAAAABZB"
    },
    "AAAAABZC": {
      "Mac": "\u109C\u109B\u109B\u10A3\u109D\u10A4\u109A\u109B\u109E\u1099\u10A8",
      "FixedDeop": "AAAAABZC"
    },
    "AAAAABZD": {
      "Mac": "\u10A5\u109B\u109A\u10A7\u109C\u10A4\u10A6\u10A0\u10A1\u10A4\u10A1",
      "FixedDeop": "AAAAABZD"
    },
    "AAAAABZE": {
      "Mac": "\u10A6\u10A1\u10A2\u10A7\u109D\u109F\u10A7\u10A2\u109A\u10A4\u109E",
      "FixedDeop": "AAAAABZE"
    },
    "AAAAABZF": {
      "Mac": "\u109C\u10A5\u10A3\u10A2\u10A4\u109B\u109F\u1099\u10A5\u10A5\u109A",
      "FixedDeop": "AAAAABZF"
    },
    "AAAAABZG": {
      "Mac": "\u109C\u10A8\u109E\u109C\u1099\u109C\u10A5\u10A3\u10A6\u10A8\u109A",
      "FixedDeop": "AAAAABZG"
    },
    "AAAAABZH": {
      "Mac": "\u10A3\u109F\u109B\u10A3\u10A3\u10A5\u10A0\u109D\u10A4\u10A2\u10A5",
      "FixedDeop": "AAAAABZH"
    },
    "AAAAABZI": {
      "Mac": "\u109D\u109F\u10A2\u1099\u10A8\u10A1\u10A6\u109E\u10A1\u109A\u109C",
      "FixedDeop": "AAAAABZI"
    },
    "AAAAABZJ": {
      "Mac": "\u109A\u10A0\u1099\u10A0\u10A2\u10A5\u109D\u1099\u109D\u109D\u109F",
      "FixedDeop": "AAAAABZJ"
    },
    "AAAAABZK": {
      "Mac": "\u10A8\u1099\u10A6\u109F\u109F\u10A8\u10A7\u109D\u10A0\u109D\u1099",
      "FixedDeop": "AAAAABZK"
    },
    "AAAAABZL": {
      "Mac": "\u10A1\u10A3\u10A3\u109C\u10A7\u10A0\u109D\u109B\u10A6\u109F\u10A1",
      "FixedDeop": "AAAAABZL"
    },
    "AAAAABZM": {
      "Mac": "\u10A5\u109E\u109C\u10A6\u10A1\u10A8\u109A\u10A8\u10A1\u109C\u10A7",
      "FixedDeop": "AAAAABZM"
    },
    "AAAAABZN": {
      "Mac": "\u109D\u10A8\u10A2\u10A0\u10A4\u109D\u10A3\u10A5\u10A5\u109A\u10A2",
      "FixedDeop": "AAAAABZN"
    },
    "AAAAABZO": {
      "Mac": "\u10A5\u10A0\u1099\u109F\u109C\u109F\u10A6\u10A4\u109A\u109C\u10A8",
      "FixedDeop": "AAAAABZO"
    },
    "AAAAABZP": {
      "Mac": "\u10A3\u109B\u10A0\u10A3\u109B\u10A5\u109F\u109E\u10A1\u10A1\u109C",
      "FixedDeop": "AAAAABZP"
    },
    "AAAAABZQ": {
      "Mac": "\u10A1\u10A5\u1099\u10A2\u109D\u10A4\u109B\u10A8\u10A0\u109D\u10A7",
      "FixedDeop": "AAAAABZQ"
    },
    "AAAAABZR": {
      "Mac": "\u10A1\u10A8\u10A8\u109D\u10A2\u10A5\u109B\u10A5\u10A3\u109D\u109D",
      "FixedDeop": "AAAAABZR"
    },
    "AAAAABZS": {
      "Mac": "\u109E\u10A4\u10A1\u10A8\u10A8\u10A8\u109E\u10A4\u109A\u109F\u10A8",
      "FixedDeop": "AAAAABZS"
    },
    "AAAAABZT": {
      "Mac": "\u10A0\u109B\u10A1\u10A4\u109D\u10A7\u10A5\u109A\u109E\u10A2\u109E",
      "FixedDeop": "AAAAABZT"
    },
    "AAAAABZU": {
      "Mac": "\u10A8\u10A7\u109F\u10A1\u10A3\u10A8\u10A8\u109F\u109F\u109E\u10A2",
      "FixedDeop": "AAAAABZU"
    },
    "AAAAABZV": {
      "Mac": "\u10A1\u10A3\u10A7\u109E\u10A8\u109A\u109F\u10A3\u10A0\u10A3\u10A1",
      "FixedDeop": "AAAAABZV"
    },
    "AAAAABZW": {
      "Mac": "\u109C\u109D\u109E\u10A3\u109F\u10A2\u10A2\u10A8\u10A0\u109D\u1099",
      "FixedDeop": "AAAAABZW"
    },
    "AAAAABZX": {
      "Mac": "\u10A8\u10A5\u10A2\u10A0\u10A7\u10A7\u10A6\u10A8\u109C\u10A0\u10A7",
      "FixedDeop": "AAAAABZX"
    },
    "AAAAABZY": {
      "Mac": "\u109B\u10A6\u10A0\u109E\u10A2\u10A0\u1099\u10A0\u10A3\u10A8\u10A0",
      "FixedDeop": "AAAAABZY"
    },
    "AAAAABZZ": {
      "Mac": "\u10A8\u10A3\u109E\u109E\u10A6\u109B\u10A1\u1099\u10A5\u109C\u10A6",
      "FixedDeop": "AAAAABZZ"
    },
    "AAAAABZa": {
      "Mac": "\u109F\u109D\u109A\u10A0\u10A2\u1099\u10A6\u10A8\u109D\u10A0\u109E",
      "FixedDeop": "AAAAABZa"
    },
    "AAAAABZb": {
      "Mac": "\u109E\u10A4\u10A2\u109B\u109B\u10A3\u10A1\u10A4\u10A7\u109E\u109A",
      "FixedDeop": "AAAAABZb"
    },
    "AAAAABZc": {
      "Mac": "\u109B\u109C\u10A8\u10A1\u109C\u109A\u10A0\u109A\u1099\u10A1\u10A6",
      "FixedDeop": "AAAAABZc"
    },
    "AAAAABZd": {
      "Mac": "\u109D\u109A\u1099\u10A6\u109C\u109D\u10A5\u10A2\u109B\u10A0\u10A6",
      "FixedDeop": "AAAAABZd"
    },
    "AAAAABZe": {
      "Mac": "\u109B\u109B\u109F\u109A\u109E\u10A4\u109E\u10A3\u10A0\u109A\u10A7",
      "FixedDeop": "AAAAABZe"
    },
    "AAAAABZf": {
      "Mac": "\u109A\u109D\u10A0\u109D\u10A2\u10A1\u109F\u109E\u10A0\u109C\u10A2",
      "FixedDeop": "AAAAABZf"
    },
    "AAAAABZg": {
      "Mac": "\u10A8\u10A7\u109A\u109A\u10A2\u10A0\u109C\u109B\u109E\u1099\u10A7",
      "FixedDeop": "AAAAABZg"
    },
    "AAAAABZh": {
      "Mac": "\u109B\u10A3\u109C\u10A6\u109F\u109E\u10A6\u109F\u10A7\u10A3\u10A6",
      "FixedDeop": "AAAAABZh"
    },
    "AAAAABZi": {
      "Mac": "\u10A1\u109C\u109E\u109D\u10A7\u109A\u1099\u10A8\u10A1\u109E\u10A8",
      "FixedDeop": "AAAAABZi"
    },
    "AAAAABZj": {
      "Mac": "\u10A8\u109E\u10A7\u10A2\u10A5\u10A2\u10A6\u10A5\u109E\u109A\u109B",
      "FixedDeop": "AAAAABZj"
    },
    "AAAAABZk": {
      "Mac": "\u109C\u10A2\u10A5\u10A2\u109E\u10A7\u10A1\u10A8\u10A7\u10A4\u10A1",
      "FixedDeop": "AAAAABZk"
    },
    "AAAAABZl": {
      "Mac": "\u10A0\u10A4\u109E\u10A8\u109A\u10A0\u10A7\u10A6\u10A8\u10A4\u109F",
      "FixedDeop": "AAAAABZl"
    },
    "AAAAABZm": {
      "Mac": "\u10A4\u1099\u10A2\u10A6\u109F\u109A\u10A4\u10A1\u10A5\u10A1\u10A0",
      "FixedDeop": "AAAAABZm"
    },
    "AAAAABZn": {
      "Mac": "\u10A2\u10A1\u10A4\u10A8\u10A5\u10A6\u10A0\u1099\u10A4\u109C\u10A0",
      "FixedDeop": "AAAAABZn"
    },
    "AAAAABZo": {
      "Mac": "\u10A5\u10A2\u109A\u10A6\u10A3\u109C\u1099\u109B\u10A7\u10A4\u10A0",
      "FixedDeop": "AAAAABZo"
    },
    "AAAAABZp": {
      "Mac": "\u109B\u10A4\u10A2\u109F\u109D\u109E\u10A3\u10A5\u1099\u10A3\u109D",
      "FixedDeop": "AAAAABZp"
    },
    "AAAAABZq": {
      "Mac": "\u10A0\u109C\u109F\u109E\u1099\u109E\u109E\u109F\u10A2\u10A5\u109D",
      "FixedDeop": "AAAAABZq"
    },
    "AAAAABZr": {
      "Mac": "\u109C\u10A7\u109E\u109A\u109A\u109F\u10A5\u109F\u109B\u10A8\u10A4",
      "FixedDeop": "AAAAABZr"
    },
    "AAAAABZs": {
      "Mac": "\u10A7\u109B\u109D\u1099\u10A0\u10A3\u1099\u109E\u109B\u10A4\u10A6",
      "FixedDeop": "AAAAABZs"
    },
    "AAAAABZt": {
      "Mac": "\u109B\u10A4\u10A1\u10A7\u109E\u109E\u109F\u109C\u1099\u10A2\u10A3",
      "FixedDeop": "AAAAABZt"
    },
    "AAAAABZu": {
      "Mac": "\u10A5\u10A4\u10A3\u109F\u10A4\u109A\u109C\u10A7\u10A7\u109A\u10A7",
      "FixedDeop": "AAAAABZu"
    },
    "AAAAABZv": {
      "Mac": "\u109C\u109D\u109C\u10A5\u10A6\u10A3\u10A0\u10A1\u109F\u109C\u109C",
      "FixedDeop": "AAAAABZv"
    },
    "AAAAABZw": {
      "Mac": "\u109C\u10A6\u109A\u10A8\u109D\u10A8\u10A1\u10A4\u1099\u10A5\u10A1",
      "FixedDeop": "AAAAABZw"
    },
    "AAAAABZx": {
      "Mac": "\u109C\u109F\u10A6\u10A0\u109A\u109D\u10A8\u109E\u10A2\u10A7\u109E",
      "FixedDeop": "AAAAABZx"
    },
    "AAAAABZy": {
      "Mac": "\u109A\u109A\u10A5\u10A2\u10A0\u109A\u109A\u10A1\u10A1\u1099\u10A4",
      "FixedDeop": "AAAAABZy"
    },
    "AAAAABZz": {
      "Mac": "\u10A3\u10A6\u10A7\u10A1\u10A7\u1099\u109A\u109C\u109A\u109F\u109B",
      "FixedDeop": "AAAAABZz"
    },
    "AAAAABaA": {
      "Mac": "\u1099\u109E\u10A4\u10A2\u10A1\u10A7\u109F\u10A2\u10A6\u109F\u109E",
      "FixedDeop": "AAAAABaA"
    },
    "AAAAABaB": {
      "Mac": "\u10A3\u10A1\u109A\u10A5\u109E\u10A2\u10A2\u109B\u10A8\u109A\u10A2",
      "FixedDeop": "AAAAABaB"
    },
    "AAAAABaC": {
      "Mac": "\u10A1\u10A5\u109A\u10A8\u1099\u10A2\u10A0\u10A4\u109C\u10A0\u10A1",
      "FixedDeop": "AAAAABaC"
    },
    "AAAAABaD": {
      "Mac": "\u10A6\u10A8\u10A3\u109C\u10A5\u10A1\u10A1\u10A3\u109B\u109E\u109E",
      "FixedDeop": "AAAAABaD"
    },
    "AAAAABaE": {
      "Mac": "\u10A6\u1099\u10A5\u10A3\u10A8\u109A\u109B\u10A5\u1099\u10A3\u10A5",
      "FixedDeop": "AAAAABaE"
    },
    "AAAAABaF": {
      "Mac": "\u10A3\u10A0\u109A\u10A0\u109B\u109C\u10A4\u10A7\u10A5\u1099\u10A2",
      "FixedDeop": "AAAAABaF"
    },
    "AAAAABaG": {
      "Mac": "\u109E\u10A8\u10A3\u10A6\u10A4\u10A5\u10A5\u10A2\u1099\u109C\u1099",
      "FixedDeop": "AAAAABaG"
    },
    "AAAAABaH": {
      "Mac": "\u109F\u10A7\u10A1\u10A5\u10A7\u109B\u109F\u10A7\u10A0\u10A0\u10A8",
      "FixedDeop": "AAAAABaH"
    },
    "AAAAABaI": {
      "Mac": "\u10A8\u109E\u10A2\u10A8\u10A0\u10A8\u109A\u109D\u10A0\u10A2\u10A1",
      "FixedDeop": "AAAAABaI"
    },
    "AAAAABaJ": {
      "Mac": "\u10A8\u10A6\u1099\u10A3\u10A4\u10A8\u10A7\u10A2\u10A8\u109A\u10A2",
      "FixedDeop": "AAAAABaJ"
    },
    "AAAAABaK": {
      "Mac": "\u109C\u10A4\u109E\u10A4\u109E\u1099\u109C\u10A0\u109C\u109C\u10A5",
      "FixedDeop": "AAAAABaK"
    },
    "AAAAABaL": {
      "Mac": "\u10A2\u10A2\u10A2\u109D\u109B\u1099\u10A4\u109C\u10A3\u10A8\u10A4",
      "FixedDeop": "AAAAABaL"
    },
    "AAAAABaM": {
      "Mac": "\u109A\u10A6\u1099\u10A6\u10A7\u109B\u109D\u10A6\u10A5\u10A8\u10A7",
      "FixedDeop": "AAAAABaM"
    },
    "AAAAABaN": {
      "Mac": "\u10A1\u10A4\u1099\u1099\u109A\u10A8\u10A7\u10A8\u109F\u109D\u10A7",
      "FixedDeop": "AAAAABaN"
    },
    "AAAAABaO": {
      "Mac": "\u109A\u10A6\u109C\u10A6\u10A6\u10A1\u10A5\u1099\u109D\u10A7\u109D",
      "FixedDeop": "AAAAABaO"
    },
    "AAAAABaP": {
      "Mac": "\u10A3\u10A0\u10A6\u10A3\u1099\u109F\u109D\u109D\u10A0\u10A1\u10A2",
      "FixedDeop": "AAAAABaP"
    },
    "AAAAABaQ": {
      "Mac": "\u10A7\u109C\u10A3\u10A3\u10A4\u10A4\u109D\u109E\u109A\u10A2\u109B",
      "FixedDeop": "AAAAABaQ"
    },
    "AAAAABaR": {
      "Mac": "\u10A5\u10A7\u10A3\u109B\u109F\u109B\u1099\u109B\u109A\u10A3\u10A5",
      "FixedDeop": "AAAAABaR"
    },
    "AAAAABaS": {
      "Mac": "\u109D\u10A5\u109B\u10A4\u109E\u10A7\u10A5\u10A3\u109D\u109C\u10A4",
      "FixedDeop": "AAAAABaS"
    },
    "AAAAABaT": {
      "Mac": "\u1099\u10A8\u10A2\u109C\u10A3\u10A3\u10A8\u10A0\u10A8\u10A5\u10A3",
      "FixedDeop": "AAAAABaT"
    },
    "AAAAABaU": {
      "Mac": "\u109E\u109E\u1099\u10A0\u109C\u10A0\u10A3\u10A6\u10A7\u10A1\u10A0",
      "FixedDeop": "AAAAABaU"
    },
    "AAAAABaV": {
      "Mac": "\u109E\u10A0\u1099\u10A0\u10A6\u10A5\u109F\u10A7\u109D\u109D\u1099",
      "FixedDeop": "AAAAABaV"
    },
    "AAAAABaW": {
      "Mac": "\u109C\u109B\u109C\u10A7\u109D\u10A2\u10A4\u109A\u109A\u109D\u10A6",
      "FixedDeop": "AAAAABaW"
    },
    "AAAAABaX": {
      "Mac": "\u109A\u10A4\u109E\u10A4\u109A\u10A7\u10A2\u10A4\u10A0\u10A6\u109E",
      "FixedDeop": "AAAAABaX"
    },
    "AAAAABaY": {
      "Mac": "\u10A0\u109E\u109F\u109B\u109E\u10A2\u10A0\u10A0\u10A1\u109F\u1099",
      "FixedDeop": "AAAAABaY"
    },
    "AAAAABaZ": {
      "Mac": "\u10A4\u109C\u10A8\u109B\u10A5\u10A1\u109B\u109F\u10A3\u109A\u10A3",
      "FixedDeop": "AAAAABaZ"
    },
    "AAAAABaa": {
      "Mac": "\u109C\u10A2\u10A8\u10A6\u10A2\u109E\u10A4\u10A2\u10A6\u109D\u109C",
      "FixedDeop": "AAAAABaa"
    },
    "AAAAABab": {
      "Mac": "\u109A\u10A8\u109D\u109A\u1099\u10A7\u10A0\u10A4\u109B\u10A1\u10A2",
      "FixedDeop": "AAAAABab"
    },
    "AAAAABac": {
      "Mac": "\u10A7\u109D\u10A3\u10A7\u10A4\u10A6\u10A5\u10A1\u10A5\u10A4\u109A",
      "FixedDeop": "AAAAABac"
    },
    "AAAAABad": {
      "Mac": "\u10A4\u1099\u109A\u10A7\u109B\u109D\u109B\u10A0\u10A1\u10A7\u109D",
      "FixedDeop": "AAAAABad"
    },
    "AAAAABae": {
      "Mac": "\u10A7\u10A7\u10A5\u109B\u10A4\u10A5\u10A4\u10A5\u109F\u10A3\u109C",
      "FixedDeop": "AAAAABae"
    },
    "AAAAABaf": {
      "Mac": "\u1099\u10A4\u10A6\u10A1\u1099\u109F\u109C\u1099\u109D\u10A6\u10A0",
      "FixedDeop": "AAAAABaf"
    },
    "AAAAABag": {
      "Mac": "\u109B\u109D\u10A1\u10A3\u10A3\u109C\u10A6\u10A7\u10A6\u10A3\u10A2",
      "FixedDeop": "AAAAABag"
    },
    "AAAAABah": {
      "Mac": "\u10A3\u109C\u109B\u109D\u10A1\u10A8\u10A3\u10A1\u109D\u10A8\u109C",
      "FixedDeop": "AAAAABah"
    },
    "AAAAABai": {
      "Mac": "\u10A3\u109E\u10A4\u109A\u10A0\u109D\u109B\u10A5\u10A1\u10A1\u109E",
      "FixedDeop": "AAAAABai"
    },
    "AAAAABaj": {
      "Mac": "\u10A5\u10A2\u10A2\u10A1\u10A2\u10A6\u109F\u109B\u10A0\u109A\u10A3",
      "FixedDeop": "AAAAABaj"
    },
    "AAAAABak": {
      "Mac": "\u10A4\u10A1\u109E\u109E\u109F\u109B\u109A\u10A5\u10A0\u10A0\u109D",
      "FixedDeop": "AAAAABak"
    },
    "AAAAABal": {
      "Mac": "\u10A1\u109A\u10A0\u1099\u109D\u10A5\u10A1\u10A1\u10A6\u10A4\u1099",
      "FixedDeop": "AAAAABal"
    },
    "AAAAABam": {
      "Mac": "\u10A3\u10A1\u109C\u10A4\u109A\u10A7\u10A2\u10A3\u10A0\u109C\u109E",
      "FixedDeop": "AAAAABam"
    },
    "AAAAABan": {
      "Mac": "\u109A\u10A4\u10A6\u10A3\u10A8\u109C\u10A1\u10A1\u10A3\u1099\u1099",
      "FixedDeop": "AAAAABan"
    },
    "AAAAABao": {
      "Mac": "\u10A8\u10A6\u10A1\u109E\u109C\u10A2\u10A5\u10A5\u1099\u10A3\u109F",
      "FixedDeop": "AAAAABao"
    },
    "AAAAABap": {
      "Mac": "\u10A2\u109F\u10A8\u109E\u109B\u10A7\u10A7\u10A0\u10A5\u10A0\u109B",
      "FixedDeop": "AAAAABap"
    },
    "AAAAABaq": {
      "Mac": "\u109B\u109F\u109A\u10A5\u109D\u10A5\u10A1\u1099\u10A6\u109F\u10A5",
      "FixedDeop": "AAAAABaq"
    },
    "AAAAABar": {
      "Mac": "\u10A0\u109E\u10A4\u10A1\u109A\u109F\u109A\u109B\u10A8\u10A3\u109D",
      "FixedDeop": "AAAAABar"
    },
    "AAAAABas": {
      "Mac": "\u10A7\u1099\u109E\u10A5\u109B\u1099\u109F\u109B\u10A4\u109D\u109C",
      "FixedDeop": "AAAAABas"
    },
    "AAAAABat": {
      "Mac": "\u10A5\u10A4\u10A2\u109C\u10A5\u109B\u10A5\u10A6\u10A0\u10A2\u109E",
      "FixedDeop": "AAAAABat"
    },
    "AAAAABau": {
      "Mac": "\u10A7\u10A1\u10A2\u109A\u10A7\u10A4\u109D\u10A2\u10A3\u10A3\u10A6",
      "FixedDeop": "AAAAABau"
    },
    "AAAAABav": {
      "Mac": "\u10A6\u109D\u109B\u109B\u10A2\u109A\u10A5\u10A3\u10A3\u10A8\u10A8",
      "FixedDeop": "AAAAABav"
    },
    "AAAAABaw": {
      "Mac": "\u10A2\u10A4\u10A5\u10A8\u10A0\u109F\u109D\u10A6\u1099\u10A2\u109E",
      "FixedDeop": "AAAAABaw"
    },
    "AAAAABax": {
      "Mac": "\u109E\u10A3\u10A6\u10A1\u10A1\u1099\u10A2\u10A2\u109A\u109F\u10A5",
      "FixedDeop": "AAAAABax"
    },
    "AAAAABay": {
      "Mac": "\u109F\u10A0\u10A6\u10A1\u10A1\u10A5\u10A4\u109E\u109C\u10A6\u109A",
      "FixedDeop": "AAAAABay"
    },
    "AAAAABaz": {
      "Mac": "\u10A5\u109E\u10A8\u10A3\u10A1\u109B\u10A7\u10A3\u109E\u10A7\u10A5",
      "FixedDeop": "AAAAABaz"
    },
    "AAAAABbA": {
      "Mac": "\u109D\u109C\u109D\u1099\u10A7\u109D\u10A2\u109E\u10A7\u1099\u10A5",
      "FixedDeop": "AAAAABbA"
    },
    "AAAAABbB": {
      "Mac": "\u109D\u109C\u109C\u109B\u10A0\u10A3\u10A3\u109F\u10A5\u109A\u109E",
      "FixedDeop": "AAAAABbB"
    },
    "AAAAABbC": {
      "Mac": "\u10A2\u109D\u10A6\u10A1\u10A2\u10A4\u10A0\u109A\u10A0\u1099\u109B",
      "FixedDeop": "AAAAABbC"
    },
    "AAAAABbD": {
      "Mac": "\u10A4\u109D\u10A2\u10A2\u109A\u1099\u10A4\u10A1\u10A8\u109A\u10A0",
      "FixedDeop": "AAAAABbD"
    },
    "AAAAABbE": {
      "Mac": "\u10A3\u10A5\u10A4\u109C\u10A7\u109E\u109D\u10A1\u10A6\u10A6\u10A5",
      "FixedDeop": "AAAAABbE"
    },
    "AAAAABbF": {
      "Mac": "\u109D\u10A1\u10A8\u1099\u109C\u10A6\u10A1\u1099\u109D\u10A6\u10A1",
      "FixedDeop": "AAAAABbF"
    },
    "AAAAABbG": {
      "Mac": "\u109C\u10A8\u10A1\u109B\u10A7\u109A\u109D\u109D\u10A0\u109C\u10A6",
      "FixedDeop": "AAAAABbG"
    }
  }
}